CryptICE/__init__.py
CryptICE-2.0.dist-info/LICENSE
CryptICE-2.0.dist-info/METADATA
CryptICE-2.0.dist-info/WHEEL
CryptICE-2.0.dist-info/top_level.txt
CryptICE-2.0.dist-info/RECORD
