Metadata-Version: 2.1
Name: CryptICE
Version: 2.0
Summary: ICE cipher for Python
Home-page: https://github.com/RenardDev/CryptICE
Author: Ren
Author-email: zeze839@gmail.com
License: MIT
Download-URL: https://github.com/RenardDev/CryptICE/releases/tag/v2.0
Platform: UNKNOWN
Classifier: Development Status :: 5 - Production/Stable
Classifier: Intended Audience :: Developers
Classifier: Topic :: Software Development
Classifier: License :: OSI Approved :: MIT License
Classifier: Programming Language :: Python :: 3
Classifier: Programming Language :: Python :: 3.4
Classifier: Programming Language :: Python :: 3.5
Classifier: Programming Language :: Python :: 3.6
Classifier: Programming Language :: Python :: 3.7
Classifier: Programming Language :: Python :: 3.8
Classifier: Programming Language :: Python :: 3.9
License-File: LICENSE
